{
    "mainBackground":"lightgray",
    "viewBox":{
        "width":94,
        "height":94,
        "x":2,
        "y":1
    },
    "gameBoard":{
        "goToButton":{
            "text":"Game Board",
            "textColor":"white",
            "background":"darkgray",
            "width":15,
            "height":5,
            "x":3,
            "y":95
        }
    },
    "cardBoard":{
        "goToButton":{
            "text":"Cards",
            "textColor":"white",
            "background":"darkgray",
            "width":15,
            "height":5,
            "x":21,
            "y":95
        }
    },
    "infoBoard":{
        "goToButton":{
            "text":"Expand Info",
            "textColor":"white",
            "background":"darkgray",
            "width":15,
            "height":5,
            "x":38,
            "y":95
        }
    }
}